pythondata_cpu_serv/__init__.py
pythondata_cpu_serv/verilog/.gitmodules
pythondata_cpu_serv/verilog/LICENSE
pythondata_cpu_serv/verilog/NEWS
pythondata_cpu_serv/verilog/README.md
pythondata_cpu_serv/verilog/serv.core
pythondata_cpu_serv/verilog/servant.core
pythondata_cpu_serv/verilog/serving.core
pythondata_cpu_serv/verilog/west.yml
pythondata_cpu_serv/verilog/.github/workflows/ci.yml
pythondata_cpu_serv/verilog/.github/workflows/lint.yml
pythondata_cpu_serv/verilog/.github/workflows/openlane.yml
pythondata_cpu_serv/verilog/.github/workflows/pages.yml
pythondata_cpu_serv/verilog/bench/servant_sim.v
pythondata_cpu_serv/verilog/bench/servant_tb.cpp
pythondata_cpu_serv/verilog/bench/servant_tb.v
pythondata_cpu_serv/verilog/bench/servant_tb_vidbo.cpp
pythondata_cpu_serv/verilog/bench/uart_decoder.v
pythondata_cpu_serv/verilog/data/ac701.xdc
pythondata_cpu_serv/verilog/data/alhambra.pcf
pythondata_cpu_serv/verilog/data/arty_a7_35t.xdc
pythondata_cpu_serv/verilog/data/ax309.ucf
pythondata_cpu_serv/verilog/data/cmod_a7_35t.xdc
pythondata_cpu_serv/verilog/data/cyc1000.sdc
pythondata_cpu_serv/verilog/data/cyc1000.tcl
pythondata_cpu_serv/verilog/data/de0_nano.sdc
pythondata_cpu_serv/verilog/data/de0_nano.tcl
pythondata_cpu_serv/verilog/data/de10_nano.sdc
pythondata_cpu_serv/verilog/data/de10_nano.tcl
pythondata_cpu_serv/verilog/data/deca.sdc
pythondata_cpu_serv/verilog/data/deca.tcl
pythondata_cpu_serv/verilog/data/ebaz4205.xdc
pythondata_cpu_serv/verilog/data/go_board.pcf
pythondata_cpu_serv/verilog/data/icebreaker.pcf
pythondata_cpu_serv/verilog/data/icestick.pcf
pythondata_cpu_serv/verilog/data/icesugar.pcf
pythondata_cpu_serv/verilog/data/icev_wireless.pcf
pythondata_cpu_serv/verilog/data/lx9_microboard.ucf
pythondata_cpu_serv/verilog/data/nexys_2.tcl
pythondata_cpu_serv/verilog/data/nexys_2.ucf
pythondata_cpu_serv/verilog/data/nexys_a7.xdc
pythondata_cpu_serv/verilog/data/orangecrab_r02.lpf
pythondata_cpu_serv/verilog/data/params.tcl
pythondata_cpu_serv-1.2.0.post146.dist-info/LICENSE
pythondata_cpu_serv-1.2.0.post146.dist-info/METADATA
pythondata_cpu_serv-1.2.0.post146.dist-info/WHEEL
pythondata_cpu_serv-1.2.0.post146.dist-info/top_level.txt
pythondata_cpu_serv-1.2.0.post146.dist-info/RECORD
