Metadata-Version: 2.1
Name: pythondata-cpu-serv
Version: 1.2.0.post146
Summary: Python module containing verilog files for serv cpu.
Home-page: https://github.com/litex-hub/pythondata-cpu-serv
Author: LiteX Authors
Author-email: litex@googlegroups.com
Project-URL: Bug Tracker, https://github.com/litex-hub/pythondata-cpu-serv/issues
Project-URL: Source Code, https://github.com/litex-hub/pythondata-cpu-serv
Classifier: Programming Language :: Python :: 3
Classifier: License :: OSI Approved :: ISC License (ISCL)
Classifier: Operating System :: OS Independent
Requires-Python: >=3.5
License-File: LICENSE
